{
  "$schema": "https://json-schema.org/draft/2020-12/schema",
  "title": "Service",
  "description": "Service schema from the Mews API.",
  "$id": "https://raw.githubusercontent.com/api-evangelist/mews-systems/refs/heads/main/json-schema/booking-engine-service-schema.json",
  "required": [
    "CreatedUtc",
    "Data",
    "EnterpriseId",
    "Id",
    "IsActive",
    "Names",
    "Ordering",
    "ShortNames"
  ],
  "type": "object",
  "properties": {},
  "additionalProperties": false,
  "x-schema-id": "Service"
}