{
  "$schema": "https://json-schema.org/draft/2020-12/schema",
  "title": "ResourceBlock",
  "description": "ResourceBlock schema from the Mews API.",
  "$id": "https://raw.githubusercontent.com/api-evangelist/mews-systems/refs/heads/main/json-schema/connector-resources-resource-block-schema.json",
  "required": [
    "AssignedResourceId",
    "CreatedUtc",
    "EndUtc",
    "EnterpriseId",
    "Id",
    "IsActive",
    "Name",
    "StartUtc",
    "Type",
    "UpdatedUtc"
  ],
  "type": "object",
  "properties": {},
  "additionalProperties": false,
  "x-schema-id": "ResourceBlock"
}