{
  "$schema": "https://json-schema.org/draft/2020-12/schema",
  "title": "Company",
  "description": "Company schema from the Mews API.",
  "$id": "https://raw.githubusercontent.com/api-evangelist/mews-systems/refs/heads/main/json-schema/connector-customers-company-schema.json",
  "required": [
    "ChainId",
    "CreditRating",
    "Id",
    "IsActive",
    "Name",
    "Number",
    "Options"
  ],
  "type": "object",
  "properties": {},
  "additionalProperties": false,
  "x-schema-id": "Company"
}